django_includefilefinder-0.1.dist-info/DESCRIPTION.rst
django_includefilefinder-0.1.dist-info/METADATA
django_includefilefinder-0.1.dist-info/RECORD
django_includefilefinder-0.1.dist-info/WHEEL
django_includefilefinder-0.1.dist-info/metadata.json
django_includefilefinder-0.1.dist-info/top_level.txt
includefilefinder/__init__.py
includefilefinder/finder.py
