Metadata-Version: 2.0
Name: django-includefilefinder
Version: 0.1
Summary: Django Include File Finder
Home-page: https://github.com/zgr3doo/django-includefilefinder
Author: Piotr Zgr3doo Rykala
Author-email: zgr3doo@gmail.com
License: MIT License
Keywords: django alerts notifications
Platform: UNKNOWN
Classifier: Programming Language :: Python
Classifier: Programming Language :: Python :: 2.5
Classifier: Programming Language :: Python :: 2.6
Classifier: Programming Language :: Python :: 2.7
Classifier: Operating System :: OS Independent
Classifier: Environment :: Web Environment
Classifier: Intended Audience :: Developers
Classifier: Framework :: Django
Classifier: License :: OSI Approved :: MIT License
Classifier: Development Status :: 3 - Alpha
Requires-Dist: django
